vinvelivaanilai/__init__.py
vinvelivaanilai/_version.py
vinvelivaanilai/orbit/__init__.py
vinvelivaanilai/orbit/predict_orbit.py
vinvelivaanilai/orbit/tle_fetch.py
vinvelivaanilai/orbit/tests/__init__.py
vinvelivaanilai/orbit/tests/test_predict_orbit.py
vinvelivaanilai/orbit/tests/test_tle_fetch.py
vinvelivaanilai/space_weather/__init__.py
vinvelivaanilai/space_weather/sw_extractor.py
vinvelivaanilai/space_weather/sw_file_fetch.py
vinvelivaanilai/space_weather/tests/__init__.py
vinvelivaanilai/space_weather/tests/test_sw_extractor.py
vinvelivaanilai/space_weather/tests/test_sw_file_fetch.py
vinvelivaanilai/storage/__init__.py
vinvelivaanilai/storage/common.py
vinvelivaanilai/storage/retrieve.py
vinvelivaanilai/storage/store.py
vinvelivaanilai/storage/tests/__init__.py
vinvelivaanilai/storage/tests/test_influxdb.py
vinvelivaanilai/storage/tests/test_retrieve.py
vinvelivaanilai-1.0.7.dist-info/LICENSE
vinvelivaanilai-1.0.7.dist-info/METADATA
vinvelivaanilai-1.0.7.dist-info/WHEEL
vinvelivaanilai-1.0.7.dist-info/top_level.txt
vinvelivaanilai-1.0.7.dist-info/RECORD
