Metadata-Version: 2.1
Name: vinvelivaanilai
Version: 1.0.7
Summary: Vinvelivaanilai
Home-page: https://gitlab.com/adithyav1511/vinvelivaanilai
Author: Adithya Venkateswaran
Author-email: adithyav1511@gmail.com
License: LGPLv3
Keywords: space weather, indices
Platform: UNKNOWN
Classifier: Development Status :: 2 - Pre-Alpha
Classifier: Intended Audience :: Developers
Classifier: License :: OSI Approved :: GNU Lesser General Public License v3 (LGPLv3)
Classifier: Programming Language :: Python :: 3
Requires-Python: >=3
License-File: LICENSE
Requires-Dist: numpy (>=1.18.4)
Requires-Dist: pandas (>=1.0.4)
Requires-Dist: influxdb-client (>=1.7.0)
Requires-Dist: astropy (>=4.0.1.post1)
Requires-Dist: poliastro (>=0.15.0)
Requires-Dist: orbit-predictor (>=1.12.0)
Requires-Dist: requests (>=2.23.0)
Requires-Dist: sphinx (>=3.1.1)
Requires-Dist: sphinx-autoapi (>=1.4.0)
Requires-Dist: sphinx-rtd-theme (>=0.5.0)
